osalgopackage_utsav/__init__.py
os_shedulingAlgo_utsav-1.0.0.dist-info/Licence.txt
os_shedulingAlgo_utsav-1.0.0.dist-info/METADATA
os_shedulingAlgo_utsav-1.0.0.dist-info/WHEEL
os_shedulingAlgo_utsav-1.0.0.dist-info/top_level.txt
os_shedulingAlgo_utsav-1.0.0.dist-info/RECORD
